nonebot_plugin_mcmotd/__init__.py
nonebot_plugin_mcmotd/commands.py
nonebot_plugin_mcmotd/config.py
nonebot_plugin_mcmotd/draw_pic.py
nonebot_plugin_mcmotd/get_motd.py
nonebot_plugin_mcmotd/manager_ip.py
nonebot_plugin_mcmotd/permission.py
nonebot_plugin_mcmotd/scope_resolver.py
nonebot_plugin_mcmotd/user_tracker.py
nonebot_plugin_mcmotd-2.0.0.dist-info/METADATA
nonebot_plugin_mcmotd-2.0.0.dist-info/WHEEL
nonebot_plugin_mcmotd-2.0.0.dist-info/licenses/LICENSE
nonebot_plugin_mcmotd-2.0.0.dist-info/RECORD
