Metadata-Version: 2.4
Name: nonebot-plugin-mcmotd
Version: 2.0.0
Summary: A NoneBot2 plugin for querying Minecraft server status and generating status images
Project-URL: homepage, https://github.com/AquaOH/nonebot-plugin-mcmotd
Project-URL: repository, https://github.com/AquaOH/nonebot-plugin-mcmotd
Project-URL: documentation, https://github.com/AquaOH/nonebot-plugin-mcmotd#readme
Project-URL: changelog, https://github.com/AquaOH/nonebot-plugin-mcmotd/releases
Project-URL: issues, https://github.com/AquaOH/nonebot-plugin-mcmotd/issues
Author-email: AquaOH <aquaoh@outlook.com>
License: MIT
License-File: LICENSE
Keywords: minecraft,motd,nonebot,nonebot2,qq-bot,server-status
Classifier: Development Status :: 4 - Beta
Classifier: License :: OSI Approved :: MIT License
Classifier: Operating System :: OS Independent
Classifier: Programming Language :: Python :: 3
Classifier: Programming Language :: Python :: 3.9
Classifier: Programming Language :: Python :: 3.10
Classifier: Programming Language :: Python :: 3.11
Classifier: Programming Language :: Python :: 3.12
Classifier: Topic :: Communications :: Chat
Classifier: Topic :: Games/Entertainment
Classifier: Topic :: Internet
Requires-Python: >=3.9
Requires-Dist: aiosqlite>=0.20.0
Requires-Dist: dnspython>=2.0.0
Requires-Dist: mcstatus>=12.0.0
Requires-Dist: nonebot-adapter-onebot>=2.4.0
Requires-Dist: nonebot-plugin-localstore>=0.4.0
Requires-Dist: nonebot2>=2.4.0
Requires-Dist: pillow>=10.0.0
Requires-Dist: pydantic
Provides-Extra: dev
Requires-Dist: black>=23.0.0; extra == 'dev'
Requires-Dist: isort>=5.12.0; extra == 'dev'
Requires-Dist: pre-commit>=3.0.0; extra == 'dev'
Requires-Dist: ruff>=0.1.0; extra == 'dev'
Provides-Extra: test
Requires-Dist: pytest-asyncio>=0.21.0; extra == 'test'
Requires-Dist: pytest-mock>=3.10.0; extra == 'test'
Requires-Dist: pytest>=7.0.0; extra == 'test'
